pymigbench/__init__.py
pymigbench/code_change.py
pymigbench/constants.py
pymigbench/database.py
pymigbench/line_range.py
pymigbench/line_replacement.py
pymigbench/migration.py
pymigbench/migration_file.py
pymigbench/parsers.py
pymigbench/types.py
pymigbench-2.2.4.dist-info/LICENSE
pymigbench-2.2.4.dist-info/METADATA
pymigbench-2.2.4.dist-info/WHEEL
pymigbench-2.2.4.dist-info/top_level.txt
pymigbench-2.2.4.dist-info/RECORD
